{"type":"coze-workflow-clipboard-data","source":{"workflowId":"7531683265519517735","spaceId":"","host":"www.coze.cn","isDouyin":false,"flowMode":0},"json":{"edges":null,"nodes":[{"blocks":[],"data":{"nodeMeta":{"description":"工作流的起始节点，用于设定启动工作流需要的信息","icon":"https://lf3-static.bytednsdoc.com/obj/eden-cn/dvsmryvd_avi_dvsm/ljhwZthlaukjlkulzlp/icon/icon-Start.png","subTitle":"","title":"开始"},"outputs":[{"name":"input","required":false,"type":"string"}]},"edges":null,"id":"100001","meta":{"position":{"x":0,"y":0}},"type":"1"},{"blocks":[],"data":{"inputs":{"inputParameters":[{"input":{"type":"string","value":{"type":"ref"}},"name":"output"}],"terminatePlan":"returnVariables"},"nodeMeta":{"description":"工作流的最终节点，用于返回工作流运行后的结果信息","icon":"https://lf3-static.bytednsdoc.com/obj/eden-cn/dvsmryvd_avi_dvsm/ljhwZthlaukjlkulzlp/icon/icon-End.png","subTitle":"","title":"结束"}},"edges":null,"id":"900001","meta":{"position":{"x":1000,"y":0}},"type":"2"}],"versions":{"loop":"v2"}}}