{"type":"coze-workflow-clipboard-data","source":{"workflowId":"7531643497457205274","spaceId":"","host":"www.coze.cn","isDouyin":false,"flowMode":0},"json":{"edges":[{"sourceNodeID":"100001","sourcePortID":"","targetNodeID":"191348"},{"sourceNodeID":"119294","sourcePortID":"","targetNodeID":"900001"},{"sourceNodeID":"191348","sourcePortID":"","targetNodeID":"126113"},{"sourceNodeID":"126113","sourcePortID":"","targetNodeID":"151463"},{"sourceNodeID":"151463","sourcePortID":"","targetNodeID":"119294"}],"nodes":[{"blocks":[],"data":{"nodeMeta":{"description":"工作流的起始节点，用于设定启动工作流需要的信息","icon":"https://lf3-static.bytednsdoc.com/obj/eden-cn/dvsmryvd_avi_dvsm/ljhwZthlaukjlkulzlp/icon/icon-Start-v2.jpg","subTitle":"","title":"开始"},"outputs":[{"defaultValue":"治愈","name":"input","required":false,"type":"string"}],"trigger_parameters":[{"name":"input","required":false,"type":"string"}]},"edges":null,"id":"100001","meta":{"canvasPosition":{"x":0,"y":0},"defaultCollapsed":false,"position":{"x":-671.1837563477714,"y":-42.11296781323054}},"type":"1"},{"blocks":[],"data":{"inputs":{"inputParameters":[{"input":{"type":"string","value":{"content":{"blockID":"151463","name":"draft_url","source":"block-output"},"rawMeta":{"type":1},"type":"ref"}},"name":"output"}],"terminatePlan":"returnVariables"},"nodeMeta":{"description":"工作流的最终节点，用于返回工作流运行后的结果信息","icon":"https://lf3-static.bytednsdoc.com/obj/eden-cn/dvsmryvd_avi_dvsm/ljhwZthlaukjlkulzlp/icon/icon-End-v2.jpg","subTitle":"","title":"结束"}},"edges":null,"id":"900001","meta":{"canvasPosition":{"x":0,"y":0},"defaultCollapsed":false,"position":{"x":1661.5954169713746,"y":-63.92226250931156}},"type":"2"},{"blocks":[],"data":{"inputs":{"note":"[{\"type\":\"paragraph\",\"children\":[{\"text\":\"背景音乐\",\"type\":\"text\"}]}]","schemaType":"slate"},"size":{"height":150,"width":240}},"edges":null,"id":"104302","meta":{"canvasPosition":{"x":0,"y":0},"defaultCollapsed":false,"position":{"x":-697.6071117088045,"y":-225.66499004738523}},"type":"31"},{"blocks":[],"data":{"inputs":{"apiParam":[{"input":{"type":"string","value":{"content":"7475829177439158307","rawMeta":{"type":1},"type":"literal"}},"name":"apiID"},{"input":{"type":"string","value":{"content":"audio_infos","rawMeta":{"type":1},"type":"literal"}},"name":"apiName"},{"input":{"type":"string","value":{"content":"7475829177439109155","rawMeta":{"type":1},"type":"literal"}},"name":"pluginID"},{"input":{"type":"string","value":{"content":"剪映小助手数据生成器","rawMeta":{"type":1},"type":"literal"}},"name":"pluginName"},{"input":{"type":"string","value":{"content":"","rawMeta":{"type":1},"type":"literal"}},"name":"pluginVersion"},{"input":{"type":"string","value":{"content":"","rawMeta":{"type":1},"type":"literal"}},"name":"tips"},{"input":{"type":"string","value":{"content":"","rawMeta":{"type":1},"type":"literal"}},"name":"outDocLink"}],"inputDefs":[{"description":"特效音，eg：教堂，默认无","input":{},"name":"audio_effect","required":false,"type":"string"},{"description":"音频列表","input":{},"name":"mp3_urls","required":true,"schema":{"assistType":0,"type":"string"},"type":"list"},{"description":"时间线","input":{},"name":"timelines","required":true,"schema":{"schema":[{"description":"结束时间","input":{},"name":"end","required":true,"type":"integer"},{"description":"开始时间","input":{},"name":"start","required":true,"type":"integer"}],"type":"object"},"type":"list"},{"description":"音量大小，0-10,默认1","input":{},"name":"volume","required":false,"type":"float"}],"inputParameters":[{"input":{"schema":{"type":"string"},"type":"list","value":{"content":{"blockID":"191348","name":"data.bgm_urls","source":"block-output"},"rawMeta":{"type":99},"type":"ref"}},"name":"mp3_urls"},{"input":{"schema":{"schema":[{"name":"end","required":false,"type":"integer"},{"name":"start","required":false,"type":"integer"}],"type":"object"},"type":"list","value":{"content":{"blockID":"191348","name":"data.timelines","source":"block-output"},"rawMeta":{"type":103},"type":"ref"}},"name":"timelines"},{"input":{"type":"float","value":{"content":0.5,"rawMeta":{"type":4},"type":"literal"}},"name":"volume"}],"settingOnError":{"processType":1,"retryTimes":0,"timeoutMs":180000}},"nodeMeta":{"description":"根据时间线制作音频数据","icon":"https://lf3-static.bytednsdoc.com/obj/eden-cn/dvsmryvd_avi_dvsm/ljhwZthlaukjlkulzlp/icon/icon-Plugin-v2.jpg","subtitle":"剪映小助手数据生成器:audio_infos","title":"audio_infos"},"outputs":[{"name":"infos","required":false,"type":"string"}]},"edges":null,"id":"126113","meta":{"canvasPosition":{"x":0,"y":0},"defaultCollapsed":false,"position":{"x":266.52121219502817,"y":-55.11296781323054}},"type":"4"},{"blocks":[],"data":{"inputs":{"apiParam":[{"input":{"type":"string","value":{"content":"7457837955684515874","rawMeta":{"type":1},"type":"literal"}},"name":"apiID"},{"input":{"type":"string","value":{"content":"create_draft","rawMeta":{"type":1},"type":"literal"}},"name":"apiName"},{"input":{"type":"string","value":{"content":"7457837925833801768","rawMeta":{"type":1},"type":"literal"}},"name":"pluginID"},{"input":{"type":"string","value":{"content":"视频合成_剪映小助手","rawMeta":{"type":1},"type":"literal"}},"name":"pluginName"},{"input":{"type":"string","value":{"content":"","rawMeta":{"type":1},"type":"literal"}},"name":"pluginVersion"},{"input":{"type":"string","value":{"content":"","rawMeta":{"type":1},"type":"literal"}},"name":"tips"},{"input":{"type":"string","value":{"content":"","rawMeta":{"type":1},"type":"literal"}},"name":"outDocLink"}],"inputDefs":[{"description":"高","input":{},"name":"height","required":false,"type":"integer"},{"description":"关联创作者","input":{},"name":"user_id","required":false,"type":"integer"},{"description":"宽","input":{},"name":"width","required":false,"type":"integer"}],"inputParameters":[],"settingOnError":{"processType":1,"retryTimes":0,"timeoutMs":180000}},"nodeMeta":{"description":"插件入口-创建草稿","icon":"https://lf3-static.bytednsdoc.com/obj/eden-cn/dvsmryvd_avi_dvsm/ljhwZthlaukjlkulzlp/icon/icon-Plugin-v2.jpg","subtitle":"视频合成_剪映小助手:create_draft","title":"create_draft"},"outputs":[{"name":"draft_url","required":false,"type":"string"},{"name":"tip_url","required":false,"type":"string"}]},"edges":null,"id":"151463","meta":{"canvasPosition":{"x":0,"y":0},"defaultCollapsed":false,"position":{"x":726.521212195028,"y":-55.11296781323054}},"type":"4"},{"blocks":[],"data":{"inputs":{"apiParam":[{"input":{"type":"string","value":{"content":"7457837925833834536","rawMeta":{"type":1},"type":"literal"}},"name":"apiID"},{"input":{"type":"string","value":{"content":"add_audios","rawMeta":{"type":1},"type":"literal"}},"name":"apiName"},{"input":{"type":"string","value":{"content":"7457837925833801768","rawMeta":{"type":1},"type":"literal"}},"name":"pluginID"},{"input":{"type":"string","value":{"content":"视频合成_剪映小助手","rawMeta":{"type":1},"type":"literal"}},"name":"pluginName"},{"input":{"type":"string","value":{"content":"","rawMeta":{"type":1},"type":"literal"}},"name":"pluginVersion"},{"input":{"type":"string","value":{"content":"","rawMeta":{"type":1},"type":"literal"}},"name":"tips"},{"input":{"type":"string","value":{"content":"","rawMeta":{"type":1},"type":"literal"}},"name":"outDocLink"}],"inputDefs":[{"description":"草稿地址，使用create_draft输出的draft_url即可","input":{},"name":"draft_url","required":true,"type":"string"},{"description":"[{\"audio_url\": \"http://example.com/audio1.mp3\",\"duration\":120,\"start\":0,\"end\":12000000,\"audio_effect\":\"教堂\"}]","input":{},"name":"audio_infos","required":true,"type":"string"}],"inputParameters":[{"input":{"type":"string","value":{"content":{"blockID":"126113","name":"infos","source":"block-output"},"rawMeta":{"type":1},"type":"ref"}},"name":"audio_infos"},{"input":{"type":"string","value":{"content":{"blockID":"151463","name":"draft_url","source":"block-output"},"rawMeta":{"type":1},"type":"ref"}},"name":"draft_url"}],"settingOnError":{"processType":1,"retryTimes":0,"timeoutMs":180000}},"nodeMeta":{"description":"批量添加音频","icon":"https://lf3-static.bytednsdoc.com/obj/eden-cn/dvsmryvd_avi_dvsm/ljhwZthlaukjlkulzlp/icon/icon-Plugin-v2.jpg","subtitle":"视频合成_剪映小助手:add_audios","title":"add_audios"},"outputs":[{"name":"draft_url","required":false,"type":"string"},{"name":"track_id","required":false,"type":"string"},{"name":"audio_ids","required":false,"schema":{"type":"string"},"type":"list"}]},"edges":null,"id":"119294","meta":{"canvasPosition":{"x":0,"y":0},"defaultCollapsed":false,"position":{"x":1186.521212195028,"y":-55.11296781323054}},"type":"4"},{"blocks":[],"data":{"inputs":{"apiParam":[{"input":{"type":"string","value":{"content":"7477778304427261963","rawMeta":{"type":1},"type":"literal"}},"name":"apiID"},{"input":{"type":"string","value":{"content":"search_bgm","rawMeta":{"type":1},"type":"literal"}},"name":"apiName"},{"input":{"type":"string","value":{"content":"7477778304427245579","rawMeta":{"type":1},"type":"literal"}},"name":"pluginID"},{"input":{"type":"string","value":{"content":"背景音乐库","rawMeta":{"type":1},"type":"literal"}},"name":"pluginName"},{"input":{"type":"string","value":{"content":"","rawMeta":{"type":1},"type":"literal"}},"name":"pluginVersion"},{"input":{"type":"string","value":{"content":"","rawMeta":{"type":1},"type":"literal"}},"name":"tips"},{"input":{"type":"string","value":{"content":"","rawMeta":{"type":1},"type":"literal"}},"name":"outDocLink"}],"inputDefs":[{"description":"关键词","input":{},"name":"keyword","required":true,"type":"string"}],"inputParameters":[{"input":{"type":"string","value":{"content":{"blockID":"100001","name":"input","source":"block-output"},"rawMeta":{"type":1},"type":"ref"}},"name":"keyword"}],"settingOnError":{"processType":1,"retryTimes":0,"timeoutMs":180000}},"nodeMeta":{"description":"根据关键词搜索背景音乐","icon":"https://lf3-static.bytednsdoc.com/obj/eden-cn/dvsmryvd_avi_dvsm/ljhwZthlaukjlkulzlp/icon/icon-Plugin-v2.jpg","subtitle":"背景音乐库:search_bgm","title":"search_bgm"},"outputs":[{"name":"data","required":false,"schema":{"schema":[{"name":"bgm_urls","required":false,"schema":{"type":"string"},"type":"list"},{"name":"cover_url","required":false,"schema":[{"name":"hd","required":false,"type":"string"},{"name":"large","required":false,"type":"string"},{"name":"medium","required":false,"type":"string"},{"name":"thumb","required":false,"type":"string"}],"type":"object"},{"name":"duration","required":false,"type":"integer"},{"name":"timelines","required":false,"schema":{"schema":[{"name":"end","required":false,"type":"integer"},{"name":"start","required":false,"type":"integer"}],"type":"object"},"type":"list"},{"name":"title","required":false,"type":"string"},{"name":"bgm_url","required":false,"type":"string"}],"type":"object"},"type":"list"},{"name":"message","required":false,"type":"string"},{"name":"success","required":false,"type":"boolean"}]},"edges":null,"id":"191348","meta":{"canvasPosition":{"x":0,"y":0},"defaultCollapsed":false,"position":{"x":-193.47878780497183,"y":-55.11296781323054}},"type":"4"}],"versions":{"loop":"v2"}}}